haystack/reverse/__init__.py
haystack/reverse/api.py
haystack/reverse/cli.py
haystack/reverse/config.py
haystack/reverse/context.py
haystack/reverse/diff.py
haystack/reverse/enumerators.py
haystack/reverse/fieldtypes.py
haystack/reverse/graph.py
haystack/reverse/lrucache.py
haystack/reverse/matchers.py
haystack/reverse/pattern.py
haystack/reverse/re_string.py
haystack/reverse/searchers.py
haystack/reverse/structure.py
haystack/reverse/utils.py
haystack/reverse/heuristics/__init__.py
haystack/reverse/heuristics/constraints.py
haystack/reverse/heuristics/dsa.py
haystack/reverse/heuristics/interfaces.py
haystack/reverse/heuristics/model.py
haystack/reverse/heuristics/pointertypes.py
haystack/reverse/heuristics/radare.py
haystack/reverse/heuristics/reversers.py
haystack/reverse/heuristics/signature.py
haystack/reverse/heuristics/data/words.100
haystack_reverse-0.42.dist-info/DESCRIPTION.rst
haystack_reverse-0.42.dist-info/METADATA
haystack_reverse-0.42.dist-info/RECORD
haystack_reverse-0.42.dist-info/WHEEL
haystack_reverse-0.42.dist-info/dependency_links.txt
haystack_reverse-0.42.dist-info/entry_points.txt
haystack_reverse-0.42.dist-info/metadata.json
haystack_reverse-0.42.dist-info/top_level.txt
