Metadata-Version: 2.0
Name: haystack-reverse
Version: 0.42
Summary: Reverse C Structures from a process' memory
Home-page: http://packages.python.org/haystack-reverse/
Author: Loic Jaquemet
Author-email: loic.jaquemet+python@gmail.com
License: GPL
Download-URL: http://github.com/trolldbois/python-haystack-reverse/tree/master
Keywords: memory,analysis,forensics,record,struct,reverse,heap
Platform: UNKNOWN
Classifier: Topic :: System :: Networking
Classifier: Topic :: Security
Classifier: Environment :: Console
Classifier: Intended Audience :: Developers
Classifier: License :: OSI Approved :: GNU General Public License (GPL)
Classifier: Programming Language :: Python
Classifier: Development Status :: 4 - Beta
Requires-Dist: haystack (>=0.42)
Requires-Dist: networkx
Requires-Dist: numpy
Requires-Dist: python-Levenshtein
